README.rst
setup.py
lib/evasion/__init__.py
lib/evasion/common/__init__.py
lib/evasion/common/log.py
lib/evasion/common/net.py
lib/evasion/common/signal.py
lib/evasion/common/webhelpers.py
lib/evasion/common/tests/__init__.py
lib/evasion/common/tests/testevasioncommon.py
lib/evasion_common.egg-info/PKG-INFO
lib/evasion_common.egg-info/SOURCES.txt
lib/evasion_common.egg-info/dependency_links.txt
lib/evasion_common.egg-info/eager_resources.txt
lib/evasion_common.egg-info/entry_points.txt
lib/evasion_common.egg-info/namespace_packages.txt
lib/evasion_common.egg-info/not-zip-safe
lib/evasion_common.egg-info/top_level.txt