Metadata-Version: 1.0
Name: evasion-common
Version: 1.0.3
Summary: Helper functions collected together from other evasion modules to aid reuse such as get_free_port() and wait_for_ready().
Home-page: http://github.com/oisinmulvihill/evasion-common/tarball/master#egg=evasion_common
Author: Oisin Mulvihill
Author-email: oisinmulvihill at gmail dot com
License: Evasion Project CDDL License
Platform: UNKNOWN
